asmr_spider/__init__.py
asmr_spider/__main__.py
asmr_spider/config.py
asmr_spider/spider.py
asmr_spider-0.3.5.dist-info/LICENSE
asmr_spider-0.3.5.dist-info/METADATA
asmr_spider-0.3.5.dist-info/WHEEL
asmr_spider-0.3.5.dist-info/entry_points.txt
asmr_spider-0.3.5.dist-info/RECORD
