Metadata-Version: 2.1
Name: asmr-spider
Version: 0.3.5
Summary: asmr.one 音声下载器
Home-page: https://github.com/tkgs0/asmr-spider
License: GPL-3.0
Keywords: ASMR,ASMR Downloader
Author: 月ヶ瀬
Requires-Python: >=3.9,<4.0
Classifier: License :: OSI Approved :: GNU General Public License v3 (GPLv3)
Classifier: Programming Language :: Python :: 3
Classifier: Programming Language :: Python :: 3.9
Classifier: Programming Language :: Python :: 3.10
Classifier: Programming Language :: Python :: 3.11
Classifier: Programming Language :: Python :: 3.12
Requires-Dist: PyYAML (>=6.0)
Requires-Dist: httpx (>=0.26.0)
Requires-Dist: loguru (>=0.7.0)
Requires-Dist: pydantic (>=2.8.0,<3.0.0)
Requires-Dist: pydub (>=0.25.1)
Requires-Dist: rich (>=13.5.0)
Requires-Dist: soundfile (>=0.12.1)
Project-URL: Repository, https://github.com/tkgs0/asmr-spider
